MofanPythonGitLinuxXilieJiaocheng20201031/README.md
MofanPythonGitLinuxXilieJiaocheng20201031/__init__.py
MofanPythonGitLinuxXilieJiaocheng20201031/__main__.py
MofanPythonGitLinuxXilieJiaocheng20201031/file.epub
MofanPythonGitLinuxXilieJiaocheng20201031/index.html
MofanPythonGitLinuxXilieJiaocheng20201031/css/__init__.py
MofanPythonGitLinuxXilieJiaocheng20201031/css/annotations.css
MofanPythonGitLinuxXilieJiaocheng20201031/css/main.css
MofanPythonGitLinuxXilieJiaocheng20201031/css/normalize.css
MofanPythonGitLinuxXilieJiaocheng20201031/css/popup.css
MofanPythonGitLinuxXilieJiaocheng20201031/font/__init__.py
MofanPythonGitLinuxXilieJiaocheng20201031/font/fontello.eot
MofanPythonGitLinuxXilieJiaocheng20201031/font/fontello.svg
MofanPythonGitLinuxXilieJiaocheng20201031/font/fontello.ttf
MofanPythonGitLinuxXilieJiaocheng20201031/font/fontello.woff
MofanPythonGitLinuxXilieJiaocheng20201031/img/__init__.py
MofanPythonGitLinuxXilieJiaocheng20201031/img/annotator-glyph-sprite.png
MofanPythonGitLinuxXilieJiaocheng20201031/img/annotator-icon-sprite.png
MofanPythonGitLinuxXilieJiaocheng20201031/img/apple-touch-icon.png
MofanPythonGitLinuxXilieJiaocheng20201031/img/cancelfullscreen.png
MofanPythonGitLinuxXilieJiaocheng20201031/img/close.png
MofanPythonGitLinuxXilieJiaocheng20201031/img/fullscreen.png
MofanPythonGitLinuxXilieJiaocheng20201031/img/loader.gif
MofanPythonGitLinuxXilieJiaocheng20201031/img/menu-icon.png
MofanPythonGitLinuxXilieJiaocheng20201031/img/save.png
MofanPythonGitLinuxXilieJiaocheng20201031/img/saved.png
MofanPythonGitLinuxXilieJiaocheng20201031/img/settings-s.png
MofanPythonGitLinuxXilieJiaocheng20201031/img/settings.png
MofanPythonGitLinuxXilieJiaocheng20201031/img/star.png
MofanPythonGitLinuxXilieJiaocheng20201031/js/__init__.py
MofanPythonGitLinuxXilieJiaocheng20201031/js/epub.js
MofanPythonGitLinuxXilieJiaocheng20201031/js/epub.min.js
MofanPythonGitLinuxXilieJiaocheng20201031/js/epub.min.map
MofanPythonGitLinuxXilieJiaocheng20201031/js/hooks.min.js
mofan_python_git_linux_xilie_jiaocheng_2020_10_31-2024.3.5.0.dist-info/METADATA
mofan_python_git_linux_xilie_jiaocheng_2020_10_31-2024.3.5.0.dist-info/WHEEL
mofan_python_git_linux_xilie_jiaocheng_2020_10_31-2024.3.5.0.dist-info/entry_points.txt
mofan_python_git_linux_xilie_jiaocheng_2020_10_31-2024.3.5.0.dist-info/top_level.txt
mofan_python_git_linux_xilie_jiaocheng_2020_10_31-2024.3.5.0.dist-info/RECORD
